pypcd4/__init__.py
pypcd4/_version.py
pypcd4/pointcloud2.py
pypcd4/py.typed
pypcd4/pypcd4.py
pypcd4-1.4.2.dist-info/METADATA
pypcd4-1.4.2.dist-info/WHEEL
pypcd4-1.4.2.dist-info/licenses/LICENSE.txt
pypcd4-1.4.2.dist-info/RECORD
