Metadata-Version: 2.3
Name: pypcd4
Version: 1.4.2
Summary: Read and write PCL .pcd files in python
Project-URL: Release Notes, https://github.com/MapIV/pypcd4/releases
Project-URL: Source, https://github.com/MapIV/pypcd4
Project-URL: Tracker, https://github.com/MapIV/pypcd4/issues
Author-email: urasakikeisuke <keisuke.urasaki@map4.jp>
License: BSD 3-Clause License
Classifier: Development Status :: 5 - Production/Stable
Classifier: Intended Audience :: Developers
Classifier: License :: OSI Approved :: BSD License
Classifier: Operating System :: MacOS :: MacOS X
Classifier: Operating System :: Microsoft :: Windows
Classifier: Operating System :: POSIX
Classifier: Programming Language :: Python :: 3 :: Only
Classifier: Programming Language :: Python :: 3.8
Classifier: Programming Language :: Python :: 3.9
Classifier: Programming Language :: Python :: 3.10
Classifier: Programming Language :: Python :: 3.11
Classifier: Programming Language :: Python :: 3.12
Classifier: Programming Language :: Python :: 3.13
Classifier: Programming Language :: Python :: Implementation :: CPython
Classifier: Topic :: Scientific/Engineering
Classifier: Topic :: Software Development :: Libraries
Classifier: Topic :: Utilities
Requires-Python: >=3.8.2
Requires-Dist: numpy>=1.21.0
Requires-Dist: pydantic<3.0.0,>=1.10.8
Requires-Dist: python-lzf; sys_platform == 'linux' and (platform_machine == 'aarch64' or platform_machine == 'arm64')
Requires-Dist: python-neo-lzf>=0.3.0; sys_platform != 'linux' or (platform_machine != 'aarch64' and platform_machine != 'arm64')
Provides-Extra: dev
Requires-Dist: mypy; extra == 'dev'
Requires-Dist: ruff; extra == 'dev'
Requires-Dist: setuptools-scm; extra == 'dev'
